gemini_video_assemble/__init__.py
gemini_video_assemble/__main__.py
gemini_video_assemble/_version.py
gemini_video_assemble/assembler.py
gemini_video_assemble/cli.py
gemini_video_assemble/config.py
gemini_video_assemble/config_store.py
gemini_video_assemble/images.py
gemini_video_assemble/media.py
gemini_video_assemble/models.py
gemini_video_assemble/music.py
gemini_video_assemble/pipeline.py
gemini_video_assemble/planner.py
gemini_video_assemble/s3_uploader.py
gemini_video_assemble/server.py
gemini_video_assemble/storage.py
gemini_video_assemble/tts.py
gemini_video_assemble/templates/config.html
gemini_video_assemble/templates/history.html
gemini_video_assemble/templates/index.html
gemini_video_assemble/templates/layout.html
gemini_video_assemble-1.0.2.dist-info/licenses/LICENSE
gemini_video_assemble-1.0.2.dist-info/METADATA
gemini_video_assemble-1.0.2.dist-info/WHEEL
gemini_video_assemble-1.0.2.dist-info/entry_points.txt
gemini_video_assemble-1.0.2.dist-info/top_level.txt
gemini_video_assemble-1.0.2.dist-info/RECORD
