Metadata-Version: 2.4
Name: gemini-video-assemble
Version: 1.0.2
Summary: Prompt-to-video assembly service powered by Gemini, packaged as an installable server.
Author: Prompt Video Authors
License-Expression: Apache-2.0
Requires-Python: >=3.10
License-File: LICENSE
Requires-Dist: Flask>=3.0.0
Requires-Dist: moviepy>=1.0.3
Requires-Dist: requests>=2.31.0
Requires-Dist: google-genai>=0.1.0
Requires-Dist: gunicorn>=21.2.0
Requires-Dist: gTTS>=2.5.1
Requires-Dist: Pillow>=10.1.0
Requires-Dist: boto3>=1.34.0
Dynamic: license-file
